{
  "hitDiceAmt" : 2,
  "hitDiceSided" : 6,
  "hitDiceModifier" : 20,
  "armor" : 30,
  "speed" : 30,
  "strength" : 16,
  "dexterity" : 11,
  "constitution" : 16,
  "intelligence" : 14,
  "wisdom" : 10,
  "charisma" : 8,
  "name" : "Frodo",
  "alignment" : "Lawful Good",
  "languages" : "[English, Elvish, Common Tongue]",
  "actions" : "",
  "strenSave" : 3,
  "dexteSave" : 0,
  "constSave" : 3,
  "intelSave" : 2,
  "wisdoSave" : 0,
  "chariSave" : -1,
  "proficiencyBonus" : 4,
  "strenMod" : 3,
  "dexteMod" : 0,
  "constMod" : 3,
  "intelMod" : 2,
  "wisdoMod" : 0,
  "chariMod" : -1,
  "acrobatics" : 0,
  "animalHandling" : 0,
  "arcana" : 2,
  "athletics" : 3,
  "deception" : -1,
  "history" : 2,
  "insight" : 0,
  "intimidation" : -1,
  "investigation" : 2,
  "medicine" : 0,
  "nature" : 2,
  "perception" : 0,
  "performance" : -1,
  "persuasion" : -1,
  "religion" : 2,
  "slightOfHand" : 0,
  "stealth" : 0,
  "survival" : 0,
  "passiveWisdom" : 15,
  "initiative" : 5,
  "experience" : 32000,
  "age" : null,
  "size" : "Small",
  "background" : "Townfolk",
  "traits" : [ ],
  "charClass" : "Messenger",
  "level" : 3,
  "race" : "Hobbit",
  "expertise" : [ ],
  "deathSaveSuccess" : 3,
  "deathSaveFail" : 3,
  "carriedGear" : "Backback",
  "maxCarry" : 100,
  "maxPushPull" : 300,
  "maxLift" : 150,
  "gp" : 2,
  "sp" : 20,
  "cp" : 43,
  "gems" : 1,
  "misc" : null,
  "armorType" : "Light Armor",
  "weapons" : [ ],
  "tools" : [ ],
  "savingThrows" : [ ],
  "skills" : [ ],
  "hitDice" : "2d6+20",
  "hp" : 100,
  "languageList" : [ "English", "Elvish", "Common Tongue" ],
  "actionsList" : [ ]
}